l10n_cuba/__init__.py
l10n_cuba/admin.py
l10n_cuba/apps.py
l10n_cuba/fields.py
l10n_cuba/validators.py
l10n_cuba/data/__init__.py
l10n_cuba/data/codigos_postales.py
l10n_cuba/data/municipios.py
l10n_cuba/data/provincias.py
l10n_cuba/migrations/0001_initial.py
l10n_cuba/migrations/0002_populate_table_provincia.py
l10n_cuba/migrations/0003_populate_table_municipio.py
l10n_cuba/migrations/0004_codigopostal.py
l10n_cuba/migrations/0005_populate_table_codigo_postal.py
l10n_cuba/migrations/0006_big_auto_field_pks.py
l10n_cuba/migrations/__init__.py
l10n_cuba/models/__init__.py
l10n_cuba/models/codigo_postal.py
l10n_cuba/models/municipio.py
l10n_cuba/models/provincia.py
django_l10n_cu-0.2.4.1.dist-info/LICENCE
django_l10n_cu-0.2.4.1.dist-info/METADATA
django_l10n_cu-0.2.4.1.dist-info/WHEEL
django_l10n_cu-0.2.4.1.dist-info/top_level.txt
django_l10n_cu-0.2.4.1.dist-info/RECORD
